classic/sql_tools/__init__.py
classic/sql_tools/module.py
classic/sql_tools/params_styles.py
classic/sql_tools/query.py
classic/sql_tools/result.py
classic/sql_tools/types.py
classic/sql_tools/templates/__init__.py
classic/sql_tools/templates/extension.py
classic/sql_tools/templates/renderer.py
classic_sql_tools-0.4.2.dist-info/licenses/LICENSE
classic_sql_tools-0.4.2.dist-info/METADATA
classic_sql_tools-0.4.2.dist-info/WHEEL
classic_sql_tools-0.4.2.dist-info/top_level.txt
classic_sql_tools-0.4.2.dist-info/RECORD
